dnnr/__init__.py
dnnr/dnnr.py
dnnr/nn_index.py
dnnr/py.typed
dnnr/scaling.py
dnnr/solver.py
dnnr-0.1.2.dist-info/LICENSE
dnnr-0.1.2.dist-info/WHEEL
dnnr-0.1.2.dist-info/METADATA
dnnr-0.1.2.dist-info/RECORD
