Metadata-Version: 2.1
Name: dnnr
Version: 0.1.2
Summary: Easy to use package of the DNNR regression.
Home-page: https://github.com/younader/dnnr
License: MIT
Author: Youssef Nadar
Author-email: youssef.nadar@fu-berlin.de
Requires-Python: >=3.7,<3.11
Classifier: Development Status :: 2 - Pre-Alpha
Classifier: Intended Audience :: Developers
Classifier: License :: OSI Approved :: MIT License
Classifier: Programming Language :: Python :: 3
Classifier: Programming Language :: Python :: 3.10
Classifier: Programming Language :: Python :: 3.7
Classifier: Programming Language :: Python :: 3.8
Classifier: Programming Language :: Python :: 3.9
Requires-Dist: annoy (>=1.17.0,<2.0.0)
Requires-Dist: numpy (>=1.21.0,<2.0.0)
Requires-Dist: scikit-learn (>=1.0.0,<2.0.0)
Requires-Dist: scipy (>=1.7.0,<2.0.0)
Requires-Dist: tqdm (>=4.64.0,<5.0.0)
